bionetgen/__init__.py
bionetgen/main.py
bionetgen/assets/BNGVERSION
bionetgen/assets/VERSION
bionetgen/assets/bionetgen-temp.ipynb
bionetgen/assets/bionetgen.ipynb
bionetgen/assets/get_version_json.py
bionetgen/assets/ghapi.json
bionetgen/atomizer/__init__.py
bionetgen/atomizer/atomizeTool.py
bionetgen/atomizer/biogrid.py
bionetgen/atomizer/bngModel.py
bionetgen/atomizer/contactMap.py
bionetgen/atomizer/contextAnalyzer.py
bionetgen/atomizer/libsbml2bngl.py
bionetgen/atomizer/parseAnnotation.py
bionetgen/atomizer/sbml2bngl.py
bionetgen/atomizer/sbml2json.py
bionetgen/atomizer/sbmlTranslator.py
bionetgen/atomizer/atomizer/__init__.py
bionetgen/atomizer/atomizer/analyzeRDF.py
bionetgen/atomizer/atomizer/analyzeSBML.py
bionetgen/atomizer/atomizer/atomizationAux.py
bionetgen/atomizer/atomizer/atomizerUtils.py
bionetgen/atomizer/atomizer/detectOntology.py
bionetgen/atomizer/atomizer/moleculeCreation.py
bionetgen/atomizer/atomizer/resolveSCT.py
bionetgen/atomizer/merging/__init__.py
bionetgen/atomizer/merging/compareNamingConventions.py
bionetgen/atomizer/merging/namingDatabase.py
bionetgen/atomizer/rulifier/__init__.py
bionetgen/atomizer/rulifier/arial10.py
bionetgen/atomizer/rulifier/compareModels.py
bionetgen/atomizer/rulifier/componentGroups.py
bionetgen/atomizer/rulifier/parameterExtraction.py
bionetgen/atomizer/rulifier/postAnalysis.py
bionetgen/atomizer/rulifier/stateTransitionDiagram.py
bionetgen/atomizer/rulifier/stdgraph.py
bionetgen/atomizer/utils/__init__.py
bionetgen/atomizer/utils/annotationComparison.py
bionetgen/atomizer/utils/annotationDeletion.py
bionetgen/atomizer/utils/annotationExtender.py
bionetgen/atomizer/utils/annotationExtractor.py
bionetgen/atomizer/utils/annotationResolver.py
bionetgen/atomizer/utils/consoleCommands.py
bionetgen/atomizer/utils/extractAtomic.py
bionetgen/atomizer/utils/modelComparison.py
bionetgen/atomizer/utils/nameNormalizer.py
bionetgen/atomizer/utils/pathwaycommons.py
bionetgen/atomizer/utils/readBNGXML.py
bionetgen-0.8.6.dist-info/LICENSE
bionetgen-0.8.6.dist-info/METADATA
bionetgen-0.8.6.dist-info/WHEEL
bionetgen-0.8.6.dist-info/entry_points.txt
bionetgen-0.8.6.dist-info/top_level.txt
bionetgen-0.8.6.dist-info/RECORD
