Metadata-Version: 2.1
Name: bionetgen
Version: 0.8.6
Summary: A simple CLI and library for the BioNetGen modeling language
Home-page: https://github.com/RuleWorld/PyBioNetGen
Author: Ali Sinan Saglam, Alex DiBiasi, and James R. Faeder
Author-email: bionetgen.main@gmail.com
License: MIT
License-File: LICENSE
Requires-Dist: cement
Requires-Dist: nbopen
Requires-Dist: numpy
Requires-Dist: pyyaml
Requires-Dist: colorlog
Requires-Dist: xmltodict
Requires-Dist: seaborn
Requires-Dist: libroadrunner
Requires-Dist: sympy
Requires-Dist: lxml
Requires-Dist: networkx
Requires-Dist: python-libsbml
Requires-Dist: pylru
Requires-Dist: pyparsing
